{
  "scene_token": "0a5c01343testtest",
  "sample_token": "0a5c01343testtest_CAM_FRONT",
  "sample_data_token": "0a5c01343testtest_CAM_FRONT_DSC01869",
  "timestamp": "DSC01869",
  "image_path": "./structured-data/0a5c01343testtest/DSC01869/CAM_FRONT_raw.jpg",
  "image_box_path": "./structured-data/0a5c01343testtest/DSC01869/CAM_FRONT_box.jpg",
  "image_width": 1752,
  "image_height": 1168,
  "cam_t": [
    1.8485903950201237,
    1.2121051145351176,
    1.8171784509695603
  ],
  "cam_r": [
    -0.11062013373823013,
    -0.0029078576848098844,
    -0.4980167529605563,
    0.8600779291122667
  ],
  "intrinsic": [
    [
      623.2202346680212,
      0.0,
      876.0
    ],
    [
      0.0,
      623.2286066112721,
      584.0
    ],
    [
      0.0,
      0.0,
      1.0
    ]
  ],
  "annos": []
}